[
    {
        "id":"pay_G11ZY646x6Afk3",
        "name":"Anonymous",
        "email":"abc@gmail.com",
        "phone":"++919876543210"
    },
    {
        "id":"pay_G11ZY646x6Afk3",
        "name":"Anonymous",
        "email":"abc@gmail.com",
        "phone":"++919876543210"
    },
    {
        "id":"pay_G11ZY646x6Afk3",
        "name":"Anonymous",
        "email":"abc@gmail.com",
        "phone":"++919876543210"
    },
    {
        "id":"pay_G11ZY646x6Afk3",
        "name":"Anonymous",
        "email":"abc@gmail.com",
        "phone":"++919876543210"
    },
    {
        "id":"pay_G11ZY646x6Afk3",
        "name":"Anonymous",
        "email":"abc@gmail.com",
        "phone":"++919876543210"
    },
    {
        "id":"pay_G11ZY646x6Afk3",
        "name":"Anonymous",
        "email":"abc@gmail.com",
        "phone":"++919876543210"
    },
    {
        "id":"pay_G11ZY646x6Afk3",
        "name":"Anonymous",
        "email":"abc@gmail.com",
        "phone":"++919876543210"
    }
]